GeoIP.conf
MANIFEST.in
README.md
dev_requirements.txt
requirements.txt
setup.cfg
setup.py
versioneer.py
csirtg_predict_api/__init__.py
csirtg_predict_api/_version.py
csirtg_predict_api/constants.py
csirtg_predict_api/domain.py
csirtg_predict_api/email.py
csirtg_predict_api/ip.py
csirtg_predict_api/url.py
csirtg_predict_api/whitelist.py
csirtg_predict_api.egg-info/PKG-INFO
csirtg_predict_api.egg-info/SOURCES.txt
csirtg_predict_api.egg-info/dependency_links.txt
csirtg_predict_api.egg-info/entry_points.txt
csirtg_predict_api.egg-info/requires.txt
csirtg_predict_api.egg-info/top_level.txt
data/whitelist.txt
test/__init__.py
test/test_httpd.py