Metadata-Version: 1.0
Name: csirtg-predict-api
Version: 0.0.0a3
Summary: CSIRTG Predict REST API Framework
Home-page: https://github.com/csirtgadgets/csirtg_predict_api
Author: Wes Young
Author-email: wes@csirtgadgets.com
License: MPL2
Keywords: network,security
Platform: UNKNOWN
